README.md
setup.py
watchtower_browser_testing/__init__.py
watchtower_browser_testing/config.py
watchtower_browser_testing/exceptions.py
watchtower_browser_testing/helpers.py
watchtower_browser_testing/testsuite.py
watchtower_browser_testing/tracking_validation.py
watchtower_browser_testing/utils.py
watchtower_browser_testing/version.py
watchtower_browser_testing.egg-info/PKG-INFO
watchtower_browser_testing.egg-info/SOURCES.txt
watchtower_browser_testing.egg-info/dependency_links.txt
watchtower_browser_testing.egg-info/requires.txt
watchtower_browser_testing.egg-info/top_level.txt
watchtower_browser_testing/templates/measurement_plan.html