Metadata-Version: 2.1
Name: watchtower-browser-testing
Version: 0.6.13
Summary: Watchtower in-browser tracking testing library, based on Playwright
Author: Jacob Noordmans
Author-email: jacob@graindataconsultants.com
License: MIT
Keywords: Watchtower
